wrightyrion/__init__.py
wrightyrion/agent.py
wrightyrion/base_class/__init__.py
wrightyrion/base_class/crawler.py
wrightyrion/base_class/exception.py
wrightyrion/base_class/page_handler.py
wrightyrion/base_class/page_parser.py
wrightyrion/browser_mgr/__init__.py
wrightyrion/browser_mgr/exception.py
wrightyrion/browser_mgr/main.py
wrightyrion/data_extractor/__init__.py
wrightyrion/data_extractor/main.py
wrightyrion/data_extractor/utils.py
wrightyrion/page_interactor/__init__.py
wrightyrion/page_interactor/main.py
wrightyrion/page_interactor/modules/__init__.py
wrightyrion/page_interactor/modules/click_handler.py
wrightyrion/page_interactor/modules/common_handler.py
wrightyrion/page_interactor/modules/handler.py
wrightyrion/page_interactor/modules/scroll_handler.py
wrightyrion-0.1.2.dist-info/METADATA
wrightyrion-0.1.2.dist-info/WHEEL
wrightyrion-0.1.2.dist-info/top_level.txt
wrightyrion-0.1.2.dist-info/RECORD
