Metadata-Version: 2.1
Name: wrightyrion
Version: 0.1.2
Author: steveflyer
Author-email: steveflyer7@gmail.com
Requires-Dist: lxml
Requires-Dist: gembox
Requires-Dist: aiofiles
Requires-Dist: playwright
Requires-Dist: setuptools
Requires-Dist: beautifulsoup4
